Metadata-Version: 2.1
Name: zabbix-agent-extension-couchdb3
Version: 1.0.1
Summary: Zabbix Agent extension to monitor CouchDB 3
Home-page: https://github.com/wanadev/zabbix-agent-extension-couchdb3
Author: Wanadev
Author-email: contact@wanadev.fr
Maintainer: Fabien LOISON
License: BSD-3-Clause
Keywords: zabbix monitoring couchdb couchdb3
Platform: UNKNOWN
Provides-Extra: dev
